[
  {
    "name": "Zarif Azher",
    "position": "Captain",
    "img": "zarif"
  },
  {
    "name": "Sritan Motati",
    "position": "Captain",
    "img": "sritan"
  },
  {
    "name": "Sanchali Banerjee",
    "position": "Teaching Coordinator",
    "img": "sanchali"
  },
  {
    "name": "Jasmine Ma",
    "position": "Treasurer",
    "img": "jasmine"
  },
  {
    "name": "Medha Pappula",
    "position": "Director  of Biocode",
    "img": "placeholder_profile"
  },
  {
    "name": "Akash Wudali",
    "position": "Director of Biocode",
    "img": "akash"
  },
  {
    "name": "Avnith Vijayram",
    "position": "Webmaster",
    "img": "avnith"
  }
]
